citation_docket/__init__.py
citation_docket/main.py
citation_docket/regexes/__init__.py
citation_docket/regexes/constructed_ac.py
citation_docket/regexes/constructed_am.py
citation_docket/regexes/constructed_bm.py
citation_docket/regexes/constructed_gr.py
citation_docket/regexes/constructed_jib.py
citation_docket/regexes/constructed_oca.py
citation_docket/regexes/constructed_pet.py
citation_docket/regexes/constructed_udk.py
citation_docket/regexes/models/__init__.py
citation_docket/regexes/models/constructor.py
citation_docket/regexes/models/docket_category.py
citation_docket/regexes/models/docket_citation.py
citation_docket/regexes/models/docket_model.py
citation_docket/regexes/models/gr_clean.py
citation_docket/regexes/models/misc/__init__.py
citation_docket/regexes/models/misc/extra.py
citation_docket/regexes/models/misc/num.py
citation_docket/regexes/models/misc/x.py
citation_docket/utils/__init__.py
citation_docket/utils/sc_website_2023.py
citation_docket/utils/simple_matcher.py
citation_docket/utils/specials.py
citation_docket-0.1.5.dist-info/LICENSE
citation_docket-0.1.5.dist-info/METADATA
citation_docket-0.1.5.dist-info/WHEEL
citation_docket-0.1.5.dist-info/RECORD
